[
  {
    "source_node": "RELEVANCE",
    "edge": "SearchProperties",
    "target_node": "SEARCH"
  },
  {
    "source_node": "RELEVANCE",
    "edge": "OpportunityScoreCalculated",
    "target_node": "ANALYTICS"
  },
  {
    "source_node": "RELEVANCE",
    "edge": "RelevanceCalculated",
    "target_node": "SEARCH"
  },
  {
    "source_node": "PAYMENTS",
    "edge": "PaymentExecuted",
    "target_node": "PAYMENTS"
  },
  {
    "source_node": "PAYMENTS",
    "edge": "PaymentExecuted",
    "target_node": "NOTIFICATIONS"
  },
  {
    "source_node": "OPPORTUNITIES",
    "edge": "CalculateRelevance",
    "target_node": "RELEVANCE"
  },
  {
    "source_node": "OPPORTUNITIES",
    "edge": "OpportunityBacked",
    "target_node": "SEARCH"
  },
  {
    "source_node": "OPPORTUNITIES",
    "edge": "AddContact",
    "target_node": "COMPANIES"
  },
  {
    "source_node": "OPPORTUNITIES",
    "edge": "OpportunityConfirmed",
    "target_node": "SEARCH"
  },
  {
    "source_node": "OPPORTUNITIES",
    "edge": "FollowUpsInfoUpdated",
    "target_node": "SEARCH"
  },
  {
    "source_node": "OPPORTUNITIES",
    "edge": "PropertyOpportunityVisited",
    "target_node": "ANALYTICS"
  },
  {
    "source_node": "OPPORTUNITIES",
    "edge": "OpportunityPaid",
    "target_node": "SEARCH"
  },
  {
    "source_node": "OPPORTUNITIES",
    "edge": "CustomerInvoiceInfoUpdated",
    "target_node": "INVOICES"
  },
  {
    "source_node": "OPPORTUNITIES",
    "edge": "CustomerInvoiceInfoUpdated",
    "target_node": "SEARCH"
  },
  {
    "source_node": "OPPORTUNITIES",
    "edge": "CustomerInvoiceInfoUpdated",
    "target_node": "NOTIFICATIONS"
  },
  {
    "source_node": "OPPORTUNITIES",
    "edge": "CustomerInvoiceInfoUpdated",
    "target_node": "NOTIFICATIONS"
  },
  {
    "source_node": "INVOICES",
    "edge": "ContactInvoiceInfoUpdated",
    "target_node": "SEARCH"
  },
  {
    "source_node": "COMMONS",
    "edge": "GetFeatureFlagActive",
    "target_node": "FEATUREFLAGS"
  },
  {
    "source_node": "RESERVATIONS",
    "edge": "PropertyReservationsUpdated",
    "target_node": "SEARCH"
  },
  {
    "source_node": "RESERVATIONS",
    "edge": "PropertyReservationsUpdated",
    "target_node": "SEARCH"
  },
  {
    "source_node": "RESERVATIONS",
    "edge": "PropertyReservationsUpdated",
    "target_node": "PROPERTIES"
  },
  {
    "source_node": "PROVIDERS",
    "edge": "GetPropertiesByProviderId",
    "target_node": "PROPERTIES"
  },
  {
    "source_node": "PROVIDERS",
    "edge": "GetProviderQualifyingQuestions",
    "target_node": "QUALIFYING"
  },
  {
    "source_node": "PROVIDERS",
    "edge": "CreateProviderBaseContact",
    "target_node": "PROVIDERS"
  },
  {
    "source_node": "PROVIDERS",
    "edge": "ProviderCreated",
    "target_node": "BUSINESSEVENTS"
  },
  {
    "source_node": "PROVIDERS",
    "edge": "ProviderCreated",
    "target_node": "SEARCH"
  },
  {
    "source_node": "PROVIDERS",
    "edge": "ProviderBasicInfoUpdated",
    "target_node": "PROVIDERS"
  },
  {
    "source_node": "PROVIDERS",
    "edge": "ProviderBasicInfoUpdated",
    "target_node": "SEARCH"
  },
  {
    "source_node": "PROVIDERS",
    "edge": "ContactAdded",
    "target_node": "SEARCH"
  },
  {
    "source_node": "PROVIDERS",
    "edge": "ContactAdded",
    "target_node": "SEARCH"
  },
  {
    "source_node": "PROVIDERS",
    "edge": "ContactAdded",
    "target_node": "SEARCH"
  },
  {
    "source_node": "PROVIDERS",
    "edge": "ContactAdded",
    "target_node": "SEARCH"
  },
  {
    "source_node": "PROVIDERS",
    "edge": "ContactAdded",
    "target_node": "SEARCH"
  },
  {
    "source_node": "PROVIDERS",
    "edge": "ContactAdded",
    "target_node": "SEARCH"
  },
  {
    "source_node": "PROVIDERS",
    "edge": "ProviderConditionsUpdated",
    "target_node": "SEARCH"
  },
  {
    "source_node": "PROVIDERS",
    "edge": "ProviderAvailabilityChecked",
    "target_node": "BUSINESSEVENTS"
  },
  {
    "source_node": "PROVIDERS",
    "edge": "ProviderInvoiceInfoUpdated",
    "target_node": "PROVIDERS"
  },
  {
    "source_node": "PROVIDERS",
    "edge": "ProviderInvoiceInfoUpdated",
    "target_node": "SEARCH"
  },
  {
    "source_node": "PROVIDERS",
    "edge": "UpdateContactInvoiceInfo",
    "target_node": "INVOICES"
  },
  {
    "source_node": "PROVIDERS",
    "edge": "GetContactInvoiceInfo",
    "target_node": "INVOICES"
  },
  {
    "source_node": "ADMIN",
    "edge": "GetFeatureFlags",
    "target_node": "FEATUREFLAGS"
  },
  {
    "source_node": "ADMIN",
    "edge": "ProposalCreated",
    "target_node": "BUSINESSEVENTS"
  },
  {
    "source_node": "ADMIN",
    "edge": "ProposalCreated",
    "target_node": "NOTIFICATIONS"
  },
  {
    "source_node": "ADMIN",
    "edge": "ProposalCreated",
    "target_node": "ANALYTICS"
  },
  {
    "source_node": "TYPEFORM",
    "edge": "CreateProposal",
    "target_node": "PROPOSALS"
  },
  {
    "source_node": "AGENTS",
    "edge": "SearchOpportunities",
    "target_node": "SEARCH"
  },
  {
    "source_node": "AGENTS",
    "edge": "AssignedRequest",
    "target_node": "NOTIFICATIONS"
  },
  {
    "source_node": "AGENTS",
    "edge": "SearchRequests",
    "target_node": "SEARCH"
  },
  {
    "source_node": "REQUESTS",
    "edge": "BasicRequestDataUpdated",
    "target_node": "SEARCH"
  },
  {
    "source_node": "PROPERTIES",
    "edge": "PropertyBasicInfoUpdated",
    "target_node": "SEARCH"
  },
  {
    "source_node": "PROPERTIES",
    "edge": "PropertyDeleted",
    "target_node": "SEARCH"
  },
  {
    "source_node": "PROPERTIES",
    "edge": "PropertyCreated",
    "target_node": "SEARCH"
  },
  {
    "source_node": "PROPERTIES",
    "edge": "PropertyPublicationStatusUpdated",
    "target_node": "SEARCH"
  },
  {
    "source_node": "PROPERTIES",
    "edge": "TagEntity",
    "target_node": "TAGGING"
  },
  {
    "source_node": "PROPERTIES",
    "edge": "GetTaggedEntities",
    "target_node": "TAGGING"
  },
  {
    "source_node": "PROPERTIES",
    "edge": "GetRelevance",
    "target_node": "RELEVANCE"
  },
  {
    "source_node": "PROPERTIES",
    "edge": "PropertyAmenitiesUpdated",
    "target_node": "SEARCH"
  },
  {
    "source_node": "PROPERTIES",
    "edge": "PropertyIcalUpdated",
    "target_node": "DEV_NULL"
  },
  {
    "source_node": "PROPERTIES",
    "edge": "PropertyPictureDeleted",
    "target_node": "SEARCH"
  },
  {
    "source_node": "PROPERTIES",
    "edge": "PropertyMainPictureUpdated",
    "target_node": "SEARCH"
  },
  {
    "source_node": "PROPERTIES",
    "edge": "PropertyPriceUpdated",
    "target_node": "SEARCH"
  },
  {
    "source_node": "NOTIFICATIONS",
    "edge": "GetFeatureFlag",
    "target_node": "FEATUREFLAGS"
  },
  {
    "source_node": "COMPANIES",
    "edge": "CompanyTermsAndConditionsUpdated",
    "target_node": "SEARCH"
  },
  {
    "source_node": "COMPANIES",
    "edge": "ContactAdded",
    "target_node": "SEARCH"
  },
  {
    "source_node": "COMPANIES",
    "edge": "ContactAdded",
    "target_node": "SEARCH"
  },
  {
    "source_node": "COMPANIES",
    "edge": "UpdateCompanyTermsAndConditions",
    "target_node": "COMPANIES"
  },
  {
    "source_node": "PROPOSALS",
    "edge": "CalculateRelevance",
    "target_node": "RELEVANCE"
  },
  {
    "source_node": "PROPOSALS",
    "edge": "GetRelevance",
    "target_node": "RELEVANCE"
  },
  {
    "source_node": "PROPOSALS",
    "edge": "ProposalCreated",
    "target_node": "BUSINESSEVENTS"
  },
  {
    "source_node": "PROPOSALS",
    "edge": "ProposalCreated",
    "target_node": "NOTIFICATIONS"
  },
  {
    "source_node": "PROPOSALS",
    "edge": "ProposalCreated",
    "target_node": "ANALYTICS"
  },
  {
    "source_node": "PROPOSALS",
    "edge": "CalculateRelevance",
    "target_node": "RELEVANCE"
  },
  {
    "source_node": "UI",
    "edge": "SearchPropertiesByRelevance",
    "target_node": "PROPERTIES"
  },
  {
    "source_node": "UI",
    "edge": "CreateNewProperty",
    "target_node": "PROPERTIES"
  },
  {
    "source_node": "UI",
    "edge": "GetPublicProperties",
    "target_node": "PROPERTIES"
  },
  {
    "source_node": "UI",
    "edge": "GetEnalquilerProperties",
    "target_node": "PROPERTIES"
  },
  {
    "source_node": "UI",
    "edge": "GetTrovitProperties",
    "target_node": "PROPERTIES"
  },
  {
    "source_node": "UI",
    "edge": "GetTucasaProperties",
    "target_node": "PROPERTIES"
  },
  {
    "source_node": "UI",
    "edge": "PostIdealistaProperties",
    "target_node": "PROPERTIES"
  },
  {
    "source_node": "UI",
    "edge": "GetPublicProperty",
    "target_node": "PROPERTIES"
  },
  {
    "source_node": "UI",
    "edge": "BatchQueryProperties",
    "target_node": "PROPERTIES"
  },
  {
    "source_node": "UI",
    "edge": "GetSimilarProperties",
    "target_node": "PROPERTIES"
  },
  {
    "source_node": "UI",
    "edge": "TagEnalquilerProperty",
    "target_node": "PROPERTIES"
  },
  {
    "source_node": "UI",
    "edge": "TagPublicProperty",
    "target_node": "PROPERTIES"
  },
  {
    "source_node": "UI",
    "edge": "DeleteProperty",
    "target_node": "PROPERTIES"
  },
  {
    "source_node": "UI",
    "edge": "UpdatePropertyBasicInfo",
    "target_node": "PROPERTIES"
  },
  {
    "source_node": "UI",
    "edge": "GetPropertyBasicInfo",
    "target_node": "PROPERTIES"
  },
  {
    "source_node": "UI",
    "edge": "UpdatePropertyAmenities",
    "target_node": "PROPERTIES"
  },
  {
    "source_node": "UI",
    "edge": "GetPropertyAmenities",
    "target_node": "PROPERTIES"
  },
  {
    "source_node": "UI",
    "edge": "UpdatePropertyPrice",
    "target_node": "PROPERTIES"
  },
  {
    "source_node": "UI",
    "edge": "GetPropertyPrice",
    "target_node": "PROPERTIES"
  },
  {
    "source_node": "UI",
    "edge": "GetPropertyIcal",
    "target_node": "PROPERTIES"
  },
  {
    "source_node": "UI",
    "edge": "UpdatePropertyIcal",
    "target_node": "PROPERTIES"
  },
  {
    "source_node": "UI",
    "edge": "GetPropertyPicturesData",
    "target_node": "PROPERTIES"
  },
  {
    "source_node": "UI",
    "edge": "UpdatePropertyMainPicture",
    "target_node": "PROPERTIES"
  },
  {
    "source_node": "UI",
    "edge": "DeletePropertyPicture",
    "target_node": "PROPERTIES"
  },
  {
    "source_node": "UI",
    "edge": "GetPropertyByProviderId",
    "target_node": "PROPERTIES"
  },
  {
    "source_node": "UI",
    "edge": "CreateOpportunity",
    "target_node": "OPPORTUNITIES"
  },
  {
    "source_node": "UI",
    "edge": "SearchOpportunities",
    "target_node": "SEARCH"
  },
  {
    "source_node": "UI",
    "edge": "OpportunityRequestDataConfirmation",
    "target_node": "NOTIFICATIONS"
  },
  {
    "source_node": "UI",
    "edge": "OpportunityCreated",
    "target_node": "RELEVANCE"
  },
  {
    "source_node": "UI",
    "edge": "CheckInOpportunityEvent",
    "target_node": "NOTIFICATIONS"
  },
  {
    "source_node": "UI",
    "edge": "CheckInOpportunityEvent",
    "target_node": "NOTIFICATIONS"
  },
  {
    "source_node": "UI",
    "edge": "BackOpportunity",
    "target_node": "OPPORTUNITIES"
  },
  {
    "source_node": "UI",
    "edge": "ConfirmOpportunity",
    "target_node": "OPPORTUNITIES"
  },
  {
    "source_node": "UI",
    "edge": "PayOpportunity",
    "target_node": "OPPORTUNITIES"
  },
  {
    "source_node": "UI",
    "edge": "UpdateCustomerInvoiceInfo",
    "target_node": "OPPORTUNITIES"
  },
  {
    "source_node": "UI",
    "edge": "GetOpportunityScore",
    "target_node": "RELEVANCE"
  },
  {
    "source_node": "UI",
    "edge": "AddRedsysPayment",
    "target_node": "PAYMENTS"
  },
  {
    "source_node": "UI",
    "edge": "GetOpportunityPayments",
    "target_node": "PAYMENTS"
  },
  {
    "source_node": "UI",
    "edge": "VisitPropertyOpportunity",
    "target_node": "OPPORTUNITIES"
  },
  {
    "source_node": "UI",
    "edge": "GetVisitedPropertyOpportunity",
    "target_node": "OPPORTUNITIES"
  },
  {
    "source_node": "UI",
    "edge": "SendAvailabilityQuery",
    "target_node": "NOTIFICATIONS"
  },
  {
    "source_node": "UI",
    "edge": "GetProposals",
    "target_node": "PROPOSALS"
  },
  {
    "source_node": "UI",
    "edge": "AllProposalsRejected",
    "target_node": "NOTIFICATIONS"
  },
  {
    "source_node": "UI",
    "edge": "OpportunityLost",
    "target_node": "NOTIFICATIONS"
  },
  {
    "source_node": "UI",
    "edge": "OpportunityLostRecover",
    "target_node": "NOTIFICATIONS"
  },
  {
    "source_node": "UI",
    "edge": "SearchProposals",
    "target_node": "SEARCH"
  },
  {
    "source_node": "UI",
    "edge": "CreateProposal",
    "target_node": "PROPOSALS"
  },
  {
    "source_node": "UI",
    "edge": "ProposalCreated",
    "target_node": "BUSINESSEVENTS"
  },
  {
    "source_node": "UI",
    "edge": "ProposalCreated",
    "target_node": "NOTIFICATIONS"
  },
  {
    "source_node": "UI",
    "edge": "ProposalCreated",
    "target_node": "ANALYTICS"
  },
  {
    "source_node": "UI",
    "edge": "SendProposalConfirmation",
    "target_node": "NOTIFICATIONS"
  },
  {
    "source_node": "UI",
    "edge": "PreparingProposal",
    "target_node": "ANALYTICS"
  },
  {
    "source_node": "UI",
    "edge": "AcceptedProposal",
    "target_node": "NOTIFICATIONS"
  },
  {
    "source_node": "UI",
    "edge": "AcceptedProposal",
    "target_node": "ANALYTICS"
  },
  {
    "source_node": "UI",
    "edge": "ShippedProposal",
    "target_node": "ANALYTICS"
  },
  {
    "source_node": "UI",
    "edge": "RejectedProposal",
    "target_node": "NOTIFICATIONS"
  },
  {
    "source_node": "UI",
    "edge": "RejectedProposal",
    "target_node": "ANALYTICS"
  },
  {
    "source_node": "UI",
    "edge": "RecoveringProposal",
    "target_node": "ANALYTICS"
  },
  {
    "source_node": "UI",
    "edge": "ContractCreated",
    "target_node": "INVOICES"
  },
  {
    "source_node": "UI",
    "edge": "PostProposalsRelevance",
    "target_node": "PROPOSALS"
  },
  {
    "source_node": "UI",
    "edge": "SendProposals",
    "target_node": "NOTIFICATIONS"
  },
  {
    "source_node": "UI",
    "edge": "TwoDaysToCheckinProposal",
    "target_node": "NOTIFICATIONS"
  },
  {
    "source_node": "UI",
    "edge": "TwoDaysToCheckinProposal",
    "target_node": "NOTIFICATIONS"
  },
  {
    "source_node": "UI",
    "edge": "CheckinInProgressProposal",
    "target_node": "NOTIFICATIONS"
  },
  {
    "source_node": "UI",
    "edge": "ThreeDaysToMonthlyPaymentProposal",
    "target_node": "NOTIFICATIONS"
  },
  {
    "source_node": "UI",
    "edge": "ThreeDaysToMonthlyPaymentProposal",
    "target_node": "NOTIFICATIONS"
  },
  {
    "source_node": "UI",
    "edge": "ThreeDaysToMonthlyPaymentProposal",
    "target_node": "NOTIFICATIONS"
  },
  {
    "source_node": "UI",
    "edge": "ThreeDaysToMonthlyPaymentProposal",
    "target_node": "NOTIFICATIONS"
  },
  {
    "source_node": "UI",
    "edge": "FiveDaysToCheckoutProposal",
    "target_node": "NOTIFICATIONS"
  },
  {
    "source_node": "UI",
    "edge": "FiveDaysToCheckoutProposal",
    "target_node": "NOTIFICATIONS"
  },
  {
    "source_node": "UI",
    "edge": "OneDayAfterCheckoutProposal",
    "target_node": "NOTIFICATIONS"
  },
  {
    "source_node": "UI",
    "edge": "OneDayAfterCheckoutProposal",
    "target_node": "NOTIFICATIONS"
  },
  {
    "source_node": "UI",
    "edge": "FirstFollowUp",
    "target_node": "NOTIFICATIONS"
  },
  {
    "source_node": "UI",
    "edge": "SecondFollowUp",
    "target_node": "NOTIFICATIONS"
  },
  {
    "source_node": "UI",
    "edge": "QualityClientProposal",
    "target_node": "NOTIFICATIONS"
  },
  {
    "source_node": "UI",
    "edge": "QualityProviderProposal",
    "target_node": "NOTIFICATIONS"
  },
  {
    "source_node": "UI",
    "edge": "GetAgents",
    "target_node": "AGENTS"
  },
  {
    "source_node": "UI",
    "edge": "AgentAutoAssignment",
    "target_node": "AGENTS"
  },
  {
    "source_node": "UI",
    "edge": "Notify",
    "target_node": "NOTIFICATIONS"
  },
  {
    "source_node": "UI",
    "edge": "ContentfulEvent",
    "target_node": "CONTENTFUL"
  },
  {
    "source_node": "UI",
    "edge": "ContentfulGetGeneralConditions",
    "target_node": "CONTENTFUL"
  },
  {
    "source_node": "UI",
    "edge": "ContentfulGetPrivacyPolicy",
    "target_node": "CONTENTFUL"
  },
  {
    "source_node": "UI",
    "edge": "SearchRequests",
    "target_node": "SEARCH"
  },
  {
    "source_node": "UI",
    "edge": "UserLogin",
    "target_node": "USERS"
  },
  {
    "source_node": "UI",
    "edge": "UpdateBasicRequestData",
    "target_node": "REQUESTS"
  },
  {
    "source_node": "UI",
    "edge": "AssignedRequest",
    "target_node": "NOTIFICATIONS"
  },
  {
    "source_node": "UI",
    "edge": "CreateProvider",
    "target_node": "PROVIDERS"
  },
  {
    "source_node": "UI",
    "edge": "CheckProviderAvailability",
    "target_node": "PROVIDERS"
  },
  {
    "source_node": "UI",
    "edge": "UpdateProviderInvoiceInfo",
    "target_node": "PROVIDERS"
  },
  {
    "source_node": "UI",
    "edge": "GetProviderInvoiceInfo",
    "target_node": "PROVIDERS"
  },
  {
    "source_node": "UI",
    "edge": "UpdateProviderConditions",
    "target_node": "PROVIDERS"
  },
  {
    "source_node": "UI",
    "edge": "GetProviderConditions",
    "target_node": "PROVIDERS"
  },
  {
    "source_node": "UI",
    "edge": "UpdateProviderBasicInfo",
    "target_node": "PROVIDERS"
  },
  {
    "source_node": "UI",
    "edge": "GetProviderBasicInfo",
    "target_node": "PROVIDERS"
  },
  {
    "source_node": "UI",
    "edge": "AddProviderQualifyingQuestions",
    "target_node": "QUALIFYING"
  },
  {
    "source_node": "UI",
    "edge": "GetProviderQualifyingQuestions",
    "target_node": "QUALIFYING"
  },
  {
    "source_node": "UI",
    "edge": "GetPropertiesByProviderHomyspaceReference",
    "target_node": "PROVIDERS"
  },
  {
    "source_node": "UI",
    "edge": "Admin_DisableProvider",
    "target_node": "ADMIN"
  },
  {
    "source_node": "UI",
    "edge": "Admin_EnableProvider",
    "target_node": "ADMIN"
  },
  {
    "source_node": "UI",
    "edge": "Admin_UpdateProviderUsesICal",
    "target_node": "ADMIN"
  },
  {
    "source_node": "UI",
    "edge": "Admin_UpdateProviderPriceType",
    "target_node": "ADMIN"
  },
  {
    "source_node": "UI",
    "edge": "Admin_UpdateProviderCommissionPercentage",
    "target_node": "ADMIN"
  },
  {
    "source_node": "UI",
    "edge": "Admin_UpdateProviderBillable",
    "target_node": "ADMIN"
  },
  {
    "source_node": "UI",
    "edge": "Admin_GenerateHangoutsLink",
    "target_node": "ADMIN"
  },
  {
    "source_node": "UI",
    "edge": "Admin_UpdatePropertyPrice",
    "target_node": "ADMIN"
  },
  {
    "source_node": "UI",
    "edge": "Admin_MigrateOrigin",
    "target_node": "ADMIN"
  },
  {
    "source_node": "UI",
    "edge": "Admin_MigratePropertyPublicationStatus",
    "target_node": "ADMIN"
  },
  {
    "source_node": "UI",
    "edge": "Admin_UpdateAvailabilityIndex",
    "target_node": "ADMIN"
  },
  {
    "source_node": "UI",
    "edge": "Admin_GetFeatureFlags",
    "target_node": "ADMIN"
  },
  {
    "source_node": "UI",
    "edge": "BusinessEventCreated",
    "target_node": "OPPORTUNITIES"
  },
  {
    "source_node": "UI",
    "edge": "BusinessEventCreated",
    "target_node": "OPPORTUNITIES"
  },
  {
    "source_node": "UI",
    "edge": "BusinessEventCreated",
    "target_node": "ANALYTICS"
  },
  {
    "source_node": "UI",
    "edge": "GetFeatureFlags",
    "target_node": "FEATUREFLAGS"
  },
  {
    "source_node": "UI",
    "edge": "SaveFeatureFlag",
    "target_node": "FEATUREFLAGS"
  },
  {
    "source_node": "UI",
    "edge": "GetFeatureFlag",
    "target_node": "FEATUREFLAGS"
  },
  {
    "source_node": "UI",
    "edge": "GetFeatureFlagActive",
    "target_node": "FEATUREFLAGS"
  },
  {
    "source_node": "UI",
    "edge": "InvoicePaid",
    "target_node": "NOTIFICATIONS"
  },
  {
    "source_node": "UI",
    "edge": "InvoicePaid",
    "target_node": "NOTIFICATIONS"
  },
  {
    "source_node": "UI",
    "edge": "InvoicePaid",
    "target_node": "NOTIFICATIONS"
  },
  {
    "source_node": "UI",
    "edge": "InvoicePaid",
    "target_node": "NOTIFICATIONS"
  },
  {
    "source_node": "UI",
    "edge": "AddCompanyQualifyingQuestions",
    "target_node": "QUALIFYING"
  },
  {
    "source_node": "UI",
    "edge": "GetCompanyQualifyingQuestions",
    "target_node": "QUALIFYING"
  },
  {
    "source_node": "UI",
    "edge": "GetReservations",
    "target_node": "RESERVATIONS"
  },
  {
    "source_node": "UI",
    "edge": "CreateReservation",
    "target_node": "RESERVATIONS"
  },
  {
    "source_node": "UI",
    "edge": "GetReservations",
    "target_node": "RESERVATIONS"
  },
  {
    "source_node": "UI",
    "edge": "CreateReservation",
    "target_node": "RESERVATIONS"
  },
  {
    "source_node": "UI",
    "edge": "DeleteReservation",
    "target_node": "RESERVATIONS"
  },
  {
    "source_node": "UI",
    "edge": "GetReservation",
    "target_node": "RESERVATIONS"
  },
  {
    "source_node": "UI",
    "edge": "UpdateReservation",
    "target_node": "RESERVATIONS"
  },
  {
    "source_node": "UI",
    "edge": "DeleteReservation",
    "target_node": "RESERVATIONS"
  },
  {
    "source_node": "UI",
    "edge": "GenerateAvailabilityLandingLink",
    "target_node": "NOTIFICATIONS"
  },
  {
    "source_node": "UI",
    "edge": "AddOpportunityReservation",
    "target_node": "RESERVATIONS"
  },
  {
    "source_node": "UI",
    "edge": "OpportunityReservationIntentionAdded",
    "target_node": "NOTIFICATIONS"
  },
  {
    "source_node": "UI",
    "edge": "AddProposalReservation",
    "target_node": "RESERVATIONS"
  },
  {
    "source_node": "UI",
    "edge": "DeleteProposalReservation",
    "target_node": "RESERVATIONS"
  },
  {
    "source_node": "UI",
    "edge": "ChangePublicationStatus",
    "target_node": "PROPERTIES"
  },
  {
    "source_node": "UI",
    "edge": "ChangePublicationStatus",
    "target_node": "PROPERTIES"
  },
  {
    "source_node": "UI",
    "edge": "SearchProperties",
    "target_node": "SEARCH"
  },
  {
    "source_node": "UI",
    "edge": "IndexPropertyCommand",
    "target_node": "SEARCH"
  },
  {
    "source_node": "UI",
    "edge": "PropertyOwnerUpdated",
    "target_node": "SEARCH"
  },
  {
    "source_node": "UI",
    "edge": "PropertyPricingStatisticsCommand",
    "target_node": "PRICING"
  },
  {
    "source_node": "UI",
    "edge": "GetProviderUsualContact",
    "target_node": "PROVIDERS"
  },
  {
    "source_node": "UI",
    "edge": "AddProviderUsualContact",
    "target_node": "PROVIDERS"
  },
  {
    "source_node": "UI",
    "edge": "GetProviderUsualContact",
    "target_node": "PROVIDERS"
  },
  {
    "source_node": "UI",
    "edge": "AddProviderUsualContact",
    "target_node": "PROVIDERS"
  },
  {
    "source_node": "UI",
    "edge": "GenerateProposalFromTypeform",
    "target_node": "TYPEFORM"
  }
]